{
  "file-explorer:move-file": [
    {
      "modifiers": [
        "Mod"
      ],
      "key": "M"
    }
  ],
  "graph:open": [],
  "graph:open-local": [
    {
      "modifiers": [
        "Mod"
      ],
      "key": "G"
    }
  ],
  "app:go-back": [
    {
      "modifiers": [
        "Ctrl"
      ],
      "key": "O"
    }
  ],
  "app:go-forward": [
    {
      "modifiers": [
        "Ctrl"
      ],
      "key": "I"
    }
  ],
  "editor:open-search-replace": [],
  "app:delete-file": [
    {
      "modifiers": [
        "Alt",
        "Mod"
      ],
      "key": "Backspace"
    }
  ]
}